observation_portal/__init__.py
observation_portal/accounts/__init__.py
observation_portal/accounts/admin.py
observation_portal/accounts/apps.py
observation_portal/accounts/backends.py
observation_portal/accounts/forms.py
observation_portal/accounts/management/__init__.py
observation_portal/accounts/management/commands/__init__.py
observation_portal/accounts/management/commands/create_application.py
observation_portal/accounts/management/commands/create_user.py
observation_portal/accounts/management/commands/generateschema_mocked.py
observation_portal/accounts/management/commands/init_e2e_credentials.py
observation_portal/accounts/management/commands/updateclientusers.py
observation_portal/accounts/migrations/0001_initial.py
observation_portal/accounts/migrations/0002_profile_terms_accepted.py
observation_portal/accounts/migrations/0003_bulk_create_users_api.py
observation_portal/accounts/migrations/__init__.py
observation_portal/accounts/models.py
observation_portal/accounts/oauth2_migrations/0001_initial.py
observation_portal/accounts/oauth2_migrations/0002_auto_20210715_0630.py
observation_portal/accounts/oauth2_migrations/0003_alter_accesstoken_user_alter_application_user_and_more.py
observation_portal/accounts/oauth2_migrations/0004_application_allowed_origins_and_more.py
observation_portal/accounts/oauth2_migrations/__init__.py
observation_portal/accounts/permissions.py
observation_portal/accounts/serializers.py
observation_portal/accounts/signals/__init__.py
observation_portal/accounts/signals/handlers.py
observation_portal/accounts/tasks.py
observation_portal/accounts/templates/auth/logged_in_state.html
observation_portal/accounts/templates/base.html
observation_portal/accounts/templates/bulkapi-account-created-email.txt
observation_portal/accounts/templates/redoc.html
observation_portal/accounts/templates/registration/activation_complete.html
observation_portal/accounts/templates/registration/activation_email.html
django_ocs_observation_portal-4.17.6.dist-info/METADATA
django_ocs_observation_portal-4.17.6.dist-info/WHEEL
django_ocs_observation_portal-4.17.6.dist-info/entry_points.txt
django_ocs_observation_portal-4.17.6.dist-info/licenses/LICENSE
django_ocs_observation_portal-4.17.6.dist-info/RECORD
