Metadata-Version: 2.4
Name: django-ocs-observation-portal
Version: 4.17.6
Summary: The Observatory Control System (OCS) Observation Portal django apps
License: GPL-3.0-only
License-File: LICENSE
Keywords: observations,astronomy,astrophysics,cosmology,science
Author: Observatory Control System Project
Author-email: ocs@lco.global
Requires-Python: >=3.8,<3.12
Classifier: Development Status :: 3 - Alpha
Classifier: Intended Audience :: Science/Research
Classifier: License :: OSI Approved :: GNU General Public License v3 (GPLv3)
Classifier: Operating System :: OS Independent
Classifier: Programming Language :: Python :: 3
Classifier: Programming Language :: Python :: 3.8
Classifier: Programming Language :: Python :: 3.9
Classifier: Programming Language :: Python :: 3.10
Classifier: Programming Language :: Python :: 3.11
Classifier: Programming Language :: Python :: 3.7
Classifier: Topic :: Scientific/Engineering :: Astronomy
Classifier: Topic :: Scientific/Engineering :: Physics
Requires-Dist: PyPDF2 (>=1.26,<1.28)
Requires-Dist: PyYAML (>=6.0,<7.0)
Requires-Dist: apscheduler (>=3.7,<3.8)
Requires-Dist: boto3 (<2.0)
Requires-Dist: cerberus (>1.0,<2.0)
Requires-Dist: django (>=4,<5)
Requires-Dist: django-bootstrap4 (<4.0)
Requires-Dist: django-cors-headers (>=3.11,<4.0)
Requires-Dist: django-dramatiq (>=0.10,<0.11)
Requires-Dist: django-extensions (>=3.1,<4.0)
Requires-Dist: django-filter (==21.1)
Requires-Dist: django-health-check (>=3.18.3,<4.0.0)
Requires-Dist: django-oauth-toolkit (>=2,<3)
Requires-Dist: django-redis-cache (>=3,<4)
Requires-Dist: django-registration-redux (>=2.9,<3.0)
Requires-Dist: django-storages (>=1.14,<2.0)
Requires-Dist: djangorestframework (>=3,<4)
Requires-Dist: dramatiq[redis,watch] (>=1.12,<2.0)
Requires-Dist: drf-yasg (>=1.20,<2.0)
Requires-Dist: gunicorn[gevent] (>=20.1,<21.0)
Requires-Dist: lcogt-logging (==0.3.2)
Requires-Dist: ocs-rise-set (>=0.6.3,<0.7.0)
Requires-Dist: opensearch-py (>=1.0,<2.0)
Requires-Dist: psycopg2-binary (>=2.9.3,<3.0.0)
Requires-Dist: redis (>=3,<4)
Requires-Dist: requests (>=2.27.1,<3.0.0)
Requires-Dist: sentry-sdk[django] (>=2.10.0,<3.0.0)
Requires-Dist: time_intervals (>=1,<2)
Requires-Dist: uritemplate (>=4.1.1,<5.0.0)
Project-URL: Homepage, https://observatorycontrolsystem.github.io
Project-URL: Repository, https://github.com/observatorycontrolsystem/observation-portal
